.gitignore
.gitlab-ci.yml
CHANGES.txt
LICENSE.txt
MANIFEST.in
README.md
environment.yml
fping.txt
requirements.txt
setup.py
untitled.txt
PyKat.egg-info/PKG-INFO
PyKat.egg-info/SOURCES.txt
PyKat.egg-info/dependency_links.txt
PyKat.egg-info/entry_points.txt
PyKat.egg-info/requires.txt
PyKat.egg-info/top_level.txt
bin/parse.kat
bin/pykat_LLO.py
bin/pykat_output.kat
bin/test_2d_plot.py
bin/test_LLO.py
bin/test_aperture.py
bin/test_beam_det.py
bin/test_beam_trace.py
bin/test_const.py
bin/test_dump.py
bin/test_fsig.py
bin/test_hg_beam.py
bin/test_hom.py
bin/test_knm.py
bin/test_map.py
bin/test_parser.py
bin/test_pass_though.py
bin/test_plot.py
bin/test_profile.py
bin/test_property.py
bin/test_put.py
bin/test_pykat_gui.py
bin/test_rad_pressure.py
bin/test_remove.py
bin/test_romhom.py
bin/test_square_knm.py
bin/test_zernike.py
examples/LLO_matched.kat
examples/beam_trace.py
examples/cavity_scan.py
examples/displacement_transfer_function.py
examples/gauss_param.py
examples/knm.py
examples/parallel_running.py
examples/pykat_plotting.html
examples/pykat_plotting.ipynb
examples/pykat_plotting_styles.ipynb
examples/template.py
examples/asc_test/OSCAR_large_tilt_ETM.txt
examples/asc_test/OSCAR_large_tilt_ITM.txt
examples/asc_test/README
examples/asc_test/asc_base.kat
examples/asc_test/asc_base_bs.kat
examples/asc_test/asc_pd_phase.py
examples/asc_test/asc_powers.py
examples/asc_test/asc_resonance.py
examples/asc_test/master.py
examples/asc_test/master1.py
examples/asc_test/master1py
examples/asc_test/master2.py
examples/asc_test/master3.py
examples/asc_test/master3_plot.py
examples/asc_test/master4.py
examples/asc_test/master4_plot.py
examples/asc_test/master5.py
examples/basic_usage/remove_add_components.py
examples/fft/phaseplate.py
examples/fft/scale_propagation.py
examples/fft/spatial_filter.py
examples/optics/cavity_w_Rc.py
examples/parallel/parallel_test.py
examples/sagnac/QN_Sagnac_25ppm_loss.dat
examples/sagnac/QN_Sagnac_lossless.dat
examples/sagnac/master.py
examples/sagnac/sagnac_base.kat
examples/surface_maps/CVI1-S1-BC.asc
examples/surface_maps/ITM04_XYZ.xyz
examples/surface_maps/surfacemaps.py
packaging/pip_distribute.sh
