Metadata-Version: 2.1
Name: PyKat
Version: 1.2.94
Summary: Python interface and tools for FINESSE
Home-page: http://pypi.python.org/pypi/PyKat/
Author: Daniel Brown
Author-email: finesse@star.sr.bham.ac.uk
License: GPL v2
License-File: LICENSE.txt
